threaded_async/__init__.py
threaded_async/async_utils.py
threaded_async/control_inversion.py
threaded_async/threaded_async.py
threaded_async/timers.py
threaded_async-1.3.dist-info/LICENSE
threaded_async-1.3.dist-info/METADATA
threaded_async-1.3.dist-info/WHEEL
threaded_async-1.3.dist-info/top_level.txt
threaded_async-1.3.dist-info/RECORD
