Metadata-Version: 2.1
Name: threaded_async
Version: 1.3
Summary: A python library for running async code in background threads.
Classifier: Programming Language :: Python :: 3
Classifier: License :: OSI Approved :: Apache Software License
Classifier: Operating System :: OS Independent
Requires-Python: >=3.8
License-File: LICENSE
